openpb/__init__.py
openpb-0.0.1.dist-info/METADATA
openpb-0.0.1.dist-info/WHEEL
openpb-0.0.1.dist-info/top_level.txt
openpb-0.0.1.dist-info/RECORD
