Metadata-Version: 2.1
Name: openpb
Version: 0.0.1
Summary: A package for efficient problem solving
Home-page: https://github.com/nposocco/openpb
Author: Nicolas Posocco
Author-email: nicolas.posocco@gmail.com
License: UNKNOWN
Project-URL: Bug Tracker, https://github.com/nposocco/openpb/issues
Platform: UNKNOWN
Classifier: Programming Language :: Python :: 3
Classifier: License :: OSI Approved :: MIT License
Classifier: Operating System :: OS Independent
Requires-Python: >=3.6
